{
    "name": "",
    "type": "directory",
    "children": [
        {
            "name": "Neural Networks and Deep Learning.pdf",
            "type": "file"
        },
        {
            "name": "Autres",
            "type": "directory",
            "children": [
                {
                    "name": "bigdata-25ntkfacts-140924143333-phpapp01.pptx",
                    "type": "file"
                },
                {
                    "name": "CDP_vs_DMP.pdf",
                    "type": "file"
                }
            ]
        },
        {
            "name": "Convolutional Neural Networks-CNN.pdf",
            "type": "file"
        },
        {
            "name": "tutoriels",
            "type": "directory",
            "children": [
                {
                    "name": "rob2-03-octave.pdf",
                    "type": "file"
                },
                {
                    "name": "Apache Hadoop 3.0.0-alpha2 \u2013 Overview.pdf",
                    "type": "file"
                },
                {
                    "name": "Python for data analysis.pdf",
                    "type": "file"
                },
                {
                    "name": "django-docs-2.2-fr.zip",
                    "type": "file"
                },
                {
                    "name": "python-2.7.13-docs-pdf-letter.zip",
                    "type": "file"
                },
                {
                    "name": "neo4j-developer-manual-3.1-javascript.pdf",
                    "type": "file"
                },
                {
                    "name": "Les bases de donn\u00e9es NoSQL et le Big Data - Rudi Bruchez.pdf",
                    "type": "file"
                },
                {
                    "name": "Matplotlib.pdf",
                    "type": "file"
                },
                {
                    "name": "django documentation _ en.pdf",
                    "type": "file"
                },
                {
                    "name": "NumPy for Matlab users \u2014 NumPy v1.15 Manual.pdf",
                    "type": "file"
                },
                {
                    "name": "apprendre_python3.pdf",
                    "type": "file"
                },
                {
                    "name": "Splunk-6.1.4-SearchReference-CommonStatsFunctions.pdf",
                    "type": "file"
                },
                {
                    "name": "python-3.6.2rc2-docs-pdf-letter.zip",
                    "type": "file"
                },
                {
                    "name": "Splunk",
                    "type": "directory",
                    "children": [
                        {
                            "name": "Splunk-6.6.0-Knowledge.pdf",
                            "type": "file"
                        },
                        {
                            "name": "Splunk-6.4.1-SearchReference-WhatsInThisManual.pdf",
                            "type": "file"
                        },
                        {
                            "name": "Splunk-6.6.0-PivotTutorial.pdf",
                            "type": "file"
                        },
                        {
                            "name": "Splunk-6.6.0-Pivot.pdf",
                            "type": "file"
                        },
                        {
                            "name": "Splunk-6.4.1-SearchReference.pdf",
                            "type": "file"
                        }
                    ]
                },
                {
                    "name": "MongoDB",
                    "type": "directory",
                    "children": [
                        {
                            "name": "MongoDB_Architecture_Guide.pdf",
                            "type": "file"
                        },
                        {
                            "name": "mongodb_tutorial.pdf",
                            "type": "file"
                        }
                    ]
                },
                {
                    "name": "Un peu de Machine Learning avec les SVM.pdf",
                    "type": "file"
                },
                {
                    "name": "python-3.6.2rc2-docs-pdf-letter",
                    "type": "directory",
                    "children": [
                        {
                            "name": "docs-pdf",
                            "type": "directory",
                            "children": [
                                {
                                    "name": "whatsnew.pdf",
                                    "type": "file"
                                },
                                {
                                    "name": "faq.pdf",
                                    "type": "file"
                                },
                                {
                                    "name": "extending.pdf",
                                    "type": "file"
                                },
                                {
                                    "name": "reference.pdf",
                                    "type": "file"
                                },
                                {
                                    "name": "howto-ipaddress.pdf",
                                    "type": "file"
                                },
                                {
                                    "name": "howto-logging.pdf",
                                    "type": "file"
                                },
                                {
                                    "name": "howto-curses.pdf",
                                    "type": "file"
                                },
                                {
                                    "name": "c-api.pdf",
                                    "type": "file"
                                },
                                {
                                    "name": "distributing.pdf",
                                    "type": "file"
                                },
                                {
                                    "name": "howto-instrumentation.pdf",
                                    "type": "file"
                                },
                                {
                                    "name": "howto-pyporting.pdf",
                                    "type": "file"
                                },
                                {
                                    "name": "howto-functional.pdf",
                                    "type": "file"
                                },
                                {
                                    "name": "howto-sorting.pdf",
                                    "type": "file"
                                },
                                {
                                    "name": "howto-clinic.pdf",
                                    "type": "file"
                                },
                                {
                                    "name": "howto-regex.pdf",
                                    "type": "file"
                                },
                                {
                                    "name": "howto-argparse.pdf",
                                    "type": "file"
                                },
                                {
                                    "name": "installing.pdf",
                                    "type": "file"
                                },
                                {
                                    "name": "library.pdf",
                                    "type": "file"
                                },
                                {
                                    "name": "howto-logging-cookbook.pdf",
                                    "type": "file"
                                },
                                {
                                    "name": "tutorial.pdf",
                                    "type": "file"
                                },
                                {
                                    "name": "howto-unicode.pdf",
                                    "type": "file"
                                },
                                {
                                    "name": "howto-urllib2.pdf",
                                    "type": "file"
                                },
                                {
                                    "name": "howto-sockets.pdf",
                                    "type": "file"
                                },
                                {
                                    "name": "howto-descriptor.pdf",
                                    "type": "file"
                                },
                                {
                                    "name": "using.pdf",
                                    "type": "file"
                                },
                                {
                                    "name": "howto-cporting.pdf",
                                    "type": "file"
                                }
                            ]
                        }
                    ]
                },
                {
                    "name": "PowerBI",
                    "type": "directory",
                    "children": [
                        {
                            "name": "Power BI Samples.zip",
                            "type": "file"
                        },
                        {
                            "name": "Samples PBIX",
                            "type": "directory",
                            "children": [
                                {
                                    "name": "Supplier-Quality-Analysis-Sample-PBIX (1).pbix",
                                    "type": "file"
                                },
                                {
                                    "name": "Supplier-Quality-Analysis-Sample-PBIX.pbix",
                                    "type": "file"
                                },
                                {
                                    "name": "Opportunity Analysis Sample PBIX.pbix",
                                    "type": "file"
                                },
                                {
                                    "name": "Retail Analysis Sample PBIX.pbix",
                                    "type": "file"
                                },
                                {
                                    "name": "Human Resources Sample PBIX.pbix",
                                    "type": "file"
                                },
                                {
                                    "name": "Procurement Analysis Sample PBIX.pbix",
                                    "type": "file"
                                },
                                {
                                    "name": "IT Spend Analysis Sample PBIX.pbix",
                                    "type": "file"
                                },
                                {
                                    "name": "Sales and Marketing Sample PBIX.pbix",
                                    "type": "file"
                                }
                            ]
                        },
                        {
                            "name": "Microsoft_Press_ebook_Introducing_Power_BI_PDF_mobile.pdf",
                            "type": "file"
                        },
                        {
                            "name": "EN-CNTNT-PowerBI-Advanced-Analytics-with-PowerBI-white-paper.pdf",
                            "type": "file"
                        }
                    ]
                },
                {
                    "name": "mongodb_tutorial.pdf",
                    "type": "file"
                },
                {
                    "name": "Business Intelligence",
                    "type": "directory",
                    "children": [
                        {
                            "name": "Data science Syllabus.pdf",
                            "type": "file"
                        },
                        {
                            "name": "Reporting with Oracle Business Intelligence User Guide.pdf",
                            "type": "file"
                        },
                        {
                            "name": "BI course.pdf",
                            "type": "file"
                        }
                    ]
                }
            ]
        },
        {
            "name": "Improving Deep Neural Networks.pdf",
            "type": "file"
        },
        {
            "name": "Skills_prediction_based_on_multi_label_resume_classification_using_CNN_with_model_interpretability (3).pdf",
            "type": "file"
        },
        {
            "name": "CRISP-DM.pdf",
            "type": "file"
        },
        {
            "name": "Livres",
            "type": "directory",
            "children": [
                {
                    "name": "Entrepreneuriat",
                    "type": "directory",
                    "children": [
                        {
                            "name": "Why the Lean-Startup.pdf",
                            "type": "file"
                        },
                        {
                            "name": "Resume- The lean Start up.pdf",
                            "type": "file"
                        },
                        {
                            "name": "IMI-Ash-Maurya-Running-Lean-Presentation.pdf",
                            "type": "file"
                        },
                        {
                            "name": "Running LEAN (76th first pages).pdf",
                            "type": "file"
                        },
                        {
                            "name": "The Lean Startup .pdf",
                            "type": "file"
                        },
                        {
                            "name": "Business Model Generation.pdf",
                            "type": "file"
                        },
                        {
                            "name": "Business Model Canvas vs Lean Canvas - Canvanizer.pdf",
                            "type": "file"
                        }
                    ]
                },
                {
                    "name": "BIG DATA",
                    "type": "directory",
                    "children": [
                        {
                            "name": "Programming Pig.pdf",
                            "type": "file"
                        },
                        {
                            "name": "OReilly Hadoop, The Definitive Guide 4th.pdf",
                            "type": "file"
                        },
                        {
                            "name": "Hadoop For Dummies, Special Edition.pdf",
                            "type": "file"
                        }
                    ]
                },
                {
                    "name": "Math\u00e9matiques",
                    "type": "directory",
                    "children": [
                        {
                            "name": "Alg\u00e8bre lin\u00e9aire I & II.pdf",
                            "type": "file"
                        },
                        {
                            "name": "Structures alg\u00e9briques #groupes,anneaux et corps.PDF",
                            "type": "file"
                        }
                    ]
                },
                {
                    "name": "Artificial Intelligence",
                    "type": "directory",
                    "children": [
                        {
                            "name": "Le plan d'echantillonage.pdf",
                            "type": "file"
                        },
                        {
                            "name": "clustering.PPT",
                            "type": "file"
                        },
                        {
                            "name": "Prentice-Hall-Series-in-Artificial-Intelligence-Stuart-Russell-Peter-Norvig-Artificial-Intelligence_-A-Modern-Approach-Prentice-Hall-2010.pdf.pdf",
                            "type": "file"
                        },
                        {
                            "name": "Similarity Measures for Categorical Data - A Comparative Evaluation.pdf",
                            "type": "file"
                        },
                        {
                            "name": "ARS-cours5-communitydetection.pdf",
                            "type": "file"
                        },
                        {
                            "name": "The Elements for Statistical Learning, Data Mining, Inference and Prediction.pdf",
                            "type": "file"
                        },
                        {
                            "name": "Probability for Statistics and Machine Learning.pdf",
                            "type": "file"
                        },
                        {
                            "name": "Partitionnement de graphes par optimisation de modularite et consensus de partitions.pdf",
                            "type": "file"
                        },
                        {
                            "name": "Using Python for machine learning.pdf",
                            "type": "file"
                        },
                        {
                            "name": "crisp-dm by the modeling agency.pdf",
                            "type": "file"
                        },
                        {
                            "name": "Probability and Statistics for Engineers and Scientists - Fouth Edition.pdf",
                            "type": "file"
                        },
                        {
                            "name": "sampling-140501134153-phpapp01.pdf",
                            "type": "file"
                        },
                        {
                            "name": "Dropout - srivastava14a.pdf",
                            "type": "file"
                        },
                        {
                            "name": "Bishop - Pattern Recognition And Machine Learning - Springer  2006.pdf",
                            "type": "file"
                        },
                        {
                            "name": "6_BC_Lec_Market_Research_sep_2011.ppt",
                            "type": "file"
                        },
                        {
                            "name": "Les_reseaux_de_neurones_artificiels.pdf",
                            "type": "file"
                        },
                        {
                            "name": "An Introduction to Information Retrieval.pdf",
                            "type": "file"
                        },
                        {
                            "name": "CRISP DM.pdf",
                            "type": "file"
                        },
                        {
                            "name": "Data Mining_ The Textbook [Aggarwal 2015-04-14].pdf",
                            "type": "file"
                        },
                        {
                            "name": "Probabilit\u00e9s ,Statistiques, Machine Learning",
                            "type": "directory",
                            "children": [
                                {
                                    "name": "Le plan d'echantillonage.pdf",
                                    "type": "file"
                                },
                                {
                                    "name": "The Elements for Statistical Learning, Data Mining, Inference and Prediction.pdf",
                                    "type": "file"
                                },
                                {
                                    "name": "Probability for Statistics and Machine Learning.pdf",
                                    "type": "file"
                                },
                                {
                                    "name": "Probability and Statistics for Engineers and Scientists - Fouth Edition.pdf",
                                    "type": "file"
                                },
                                {
                                    "name": "sampling-140501134153-phpapp01.pdf",
                                    "type": "file"
                                },
                                {
                                    "name": "Bishop - Pattern Recognition And Machine Learning - Springer  2006.pdf",
                                    "type": "file"
                                },
                                {
                                    "name": "6_BC_Lec_Market_Research_sep_2011.ppt",
                                    "type": "file"
                                },
                                {
                                    "name": "An Introduction to Information Retrieval.pdf",
                                    "type": "file"
                                },
                                {
                                    "name": "Python_Machine_Learning_Sebastian_Raschka.pdf",
                                    "type": "file"
                                },
                                {
                                    "name": "An Introduction to Statistical Learning.pdf",
                                    "type": "file"
                                },
                                {
                                    "name": "Introduction to Probability and Statistics Using R.pdf",
                                    "type": "file"
                                },
                                {
                                    "name": "A Modern Introduction to Probability and Statistics.pdf",
                                    "type": "file"
                                },
                                {
                                    "name": "Mining of Massives Datasets.pdf",
                                    "type": "file"
                                }
                            ]
                        },
                        {
                            "name": "Python_Machine_Learning_Sebastian_Raschka.pdf",
                            "type": "file"
                        },
                        {
                            "name": "D\u00e9tection de communaut\u00e9s dans les grands graphes d'interactions (multiplexes)  \u00e9tat de l'art.pdf",
                            "type": "file"
                        },
                        {
                            "name": "Regularization Techniques for Learning with Matrices.pdf",
                            "type": "file"
                        },
                        {
                            "name": "Partitionnement et analyse de graphes.PDF",
                            "type": "file"
                        },
                        {
                            "name": "An Introduction to Statistical Learning.pdf",
                            "type": "file"
                        },
                        {
                            "name": "Introduction to Probability and Statistics Using R.pdf",
                            "type": "file"
                        },
                        {
                            "name": "Mining Text Data _ Charu Aggarwal_ ChengXiang Zhai.pdf",
                            "type": "file"
                        },
                        {
                            "name": "Detection de communautes, disjointes ou chevauchantes, dans les reseaux.pdf",
                            "type": "file"
                        },
                        {
                            "name": "STATISTIQUE DESCRIPTIVE.pdf",
                            "type": "file"
                        },
                        {
                            "name": "A Modern Introduction to Probability and Statistics.pdf",
                            "type": "file"
                        },
                        {
                            "name": "r\u00e9seaux de neurones et connexionnisme.pdf",
                            "type": "file"
                        },
                        {
                            "name": "Python Data Science Cookbook.pdf.pdf",
                            "type": "file"
                        },
                        {
                            "name": "Feature selection, L1 vs L2 regularization, and rotational invariance.pdf",
                            "type": "file"
                        },
                        {
                            "name": "Kernel Methods and Machine Learning.pdf",
                            "type": "file"
                        },
                        {
                            "name": "Mining of Massives Datasets.pdf",
                            "type": "file"
                        },
                        {
                            "name": "Word vectorization.pdf",
                            "type": "file"
                        }
                    ]
                },
                {
                    "name": "Business analysis and customer service",
                    "type": "directory",
                    "children": [
                        {
                            "name": "The Business Analysis Process_ 8 Steps to Being an Effective Business Analyst.pdf",
                            "type": "file"
                        },
                        {
                            "name": "Business_Process_Mapping.pdf",
                            "type": "file"
                        }
                    ]
                },
                {
                    "name": "documentation et commandes",
                    "type": "directory",
                    "children": [
                        {
                            "name": "Apache Hadoop 3.0.0-alpha2 \u2013 Overview.pdf",
                            "type": "file"
                        },
                        {
                            "name": "Splunk",
                            "type": "directory",
                            "children": [
                                {
                                    "name": "Splunk-6.6.0-Knowledge.pdf",
                                    "type": "file"
                                },
                                {
                                    "name": "Splunk-6.4.1-SearchReference-WhatsInThisManual.pdf",
                                    "type": "file"
                                },
                                {
                                    "name": "Splunk-6.6.0-PivotTutorial.pdf",
                                    "type": "file"
                                },
                                {
                                    "name": "Splunk-6.6.0-Pivot.pdf",
                                    "type": "file"
                                },
                                {
                                    "name": "Splunk-6.4.1-SearchReference.pdf",
                                    "type": "file"
                                }
                            ]
                        },
                        {
                            "name": "MongoDB",
                            "type": "directory",
                            "children": [
                                {
                                    "name": "MongoDB_Architecture_Guide.pdf",
                                    "type": "file"
                                },
                                {
                                    "name": "mongodb_tutorial.pdf",
                                    "type": "file"
                                }
                            ]
                        }
                    ]
                },
                {
                    "name": "Genie Logiciel",
                    "type": "directory",
                    "children": [
                        {
                            "name": "Processus de d\u00e9veloppement logiciel(software process).pdf",
                            "type": "file"
                        },
                        {
                            "name": "Processus de d\u00e9veloppement Cycles de vies.pdf",
                            "type": "file"
                        },
                        {
                            "name": "Ing\u00e9nierie des besoins.pdf",
                            "type": "file"
                        }
                    ]
                },
                {
                    "name": "bigdata2016.pdf",
                    "type": "file"
                },
                {
                    "name": "Banque et Finances",
                    "type": "directory",
                    "children": [
                        {
                            "name": "remise_documentaire.pdf",
                            "type": "file"
                        },
                        {
                            "name": "credit_documentaire.pdf",
                            "type": "file"
                        }
                    ]
                },
                {
                    "name": "Memoires",
                    "type": "directory",
                    "children": [
                        {
                            "name": "M\u00e9moire_de_fin_detude_MBA_MBOGNE_final.pdf",
                            "type": "file"
                        },
                        {
                            "name": "memoire_NFOTABONG.pdf",
                            "type": "file"
                        },
                        {
                            "name": "M_moire_Polytech_Yaound_.pdf",
                            "type": "file"
                        }
                    ]
                },
                {
                    "name": "BI.pdf",
                    "type": "file"
                },
                {
                    "name": "Algorithm",
                    "type": "directory",
                    "children": [
                        {
                            "name": "Data Structures and Algorithms in Python.pdf",
                            "type": "file"
                        }
                    ]
                },
                {
                    "name": "Marketing",
                    "type": "directory",
                    "children": [
                        {
                            "name": "An Introduction to Marketing Research.pdf",
                            "type": "file"
                        },
                        {
                            "name": "Artech_House_Successful_Marketing_Strategy_for_High-Tech_Firms_3rd.pdf",
                            "type": "file"
                        },
                        {
                            "name": "Marketing Research & Developing A Marketing Plan.pdf",
                            "type": "file"
                        },
                        {
                            "name": "Essentials of Marketing Research.pdf",
                            "type": "file"
                        },
                        {
                            "name": "Basic Marketing Research (Volume 1) - A handbook for research professionals.pdf",
                            "type": "file"
                        },
                        {
                            "name": "QualtricsSurveySoftware.pdf",
                            "type": "file"
                        },
                        {
                            "name": "A Practical Guide to Market Research.pdf",
                            "type": "file"
                        }
                    ]
                }
            ]
        },
        {
            "name": "Structuring your Machine Learning Project.pdf",
            "type": "file"
        },
        {
            "name": "Mining Text Data _ Charu Aggarwal_ ChengXiang Zhai.pdf",
            "type": "file"
        },
        {
            "name": "Articles and white paper",
            "type": "directory",
            "children": [
                {
                    "name": "BodyPartRecognition using random forest by Microsoft.pdf",
                    "type": "file"
                },
                {
                    "name": "Review on Classification Algorithms in Data Mining.pdf",
                    "type": "file"
                },
                {
                    "name": "measures.pdf",
                    "type": "file"
                },
                {
                    "name": "Analyse de donn\u00e9es et machine learning",
                    "type": "directory",
                    "children": [
                        {
                            "name": "A Neural Algorithm of Artistic Style paper.pdf",
                            "type": "file"
                        },
                        {
                            "name": "FaceNet - A Unified Embedding for Face Recognition and Clustering.pdf",
                            "type": "file"
                        },
                        {
                            "name": "Deep Residual Learning for Image Recognition.pdf",
                            "type": "file"
                        },
                        {
                            "name": "YOLO_ YouOnlyLookOnce_Object_Detection.pdf",
                            "type": "file"
                        },
                        {
                            "name": "Siamese Convolutional Neural Networks for Authorship Verification.pdf",
                            "type": "file"
                        },
                        {
                            "name": "Dropout_A Simple Way to Prevent Neural Networks from.pdf",
                            "type": "file"
                        },
                        {
                            "name": "Deepface-closing-the-gap-to-human-level-performance-in-face-verification.pdf",
                            "type": "file"
                        },
                        {
                            "name": "A Neural Algorithm of Artistic Style.pdf",
                            "type": "file"
                        },
                        {
                            "name": "Rob Fergus- Visualizing and Understanding Convolutional Networks.pdf",
                            "type": "file"
                        },
                        {
                            "name": "Siamese Neural Networks for One-Shot Image Recognition.pdf",
                            "type": "file"
                        },
                        {
                            "name": "Convolutional Neural Networks for Sentence Classification - Yoon Kim.pdf",
                            "type": "file"
                        },
                        {
                            "name": "OverFeat_Integrated Recognition, Localization and Detection.pdf",
                            "type": "file"
                        }
                    ]
                }
            ]
        },
        {
            "name": "Natural Language Processing-Building Sequence Models.pdf",
            "type": "file"
        },
        {
            "name": "Cheatset",
            "type": "directory",
            "children": [
                {
                    "name": "R-data-wrangling-cheatsheet.pdf",
                    "type": "file"
                }
            ]
        }
    ]
}
